pygeoogc/__init__.py
pygeoogc/cache_keys.py
pygeoogc/core.py
pygeoogc/exceptions.py
pygeoogc/print_versions.py
pygeoogc/py.typed
pygeoogc/pygeoogc.py
pygeoogc/utils.py
pygeoogc-0.19.4.dist-info/METADATA
pygeoogc-0.19.4.dist-info/WHEEL
pygeoogc-0.19.4.dist-info/licenses/AUTHORS.rst
pygeoogc-0.19.4.dist-info/licenses/LICENSE
pygeoogc-0.19.4.dist-info/RECORD
