Metadata-Version: 2.4
Name: pygeoogc
Version: 0.19.4
Summary: An interface to ArcGIS RESTful-, WFS-, and WMS-based services.
Project-URL: Changelog, https://docs.hyriver.io/changelogs/pygeoogc.html
Project-URL: CI, https://github.com/hyriver/pygeoogc/actions
Project-URL: Homepage, https://docs.hyriver.io/readme/pygeoogc.html
Project-URL: Issues, https://github.com/hyriver/pygeoogc/issues
Author-email: Taher Chegini <cheginit@gmail.com>
License: MIT
License-File: AUTHORS.rst
License-File: LICENSE
Classifier: Development Status :: 4 - Beta
Classifier: Intended Audience :: Science/Research
Classifier: License :: OSI Approved :: MIT License
Classifier: Operating System :: OS Independent
Classifier: Programming Language :: Python
Classifier: Programming Language :: Python :: 3 :: Only
Classifier: Programming Language :: Python :: 3.9
Classifier: Programming Language :: Python :: 3.10
Classifier: Programming Language :: Python :: 3.11
Classifier: Programming Language :: Python :: 3.12
Classifier: Programming Language :: Python :: 3.13
Classifier: Topic :: Scientific/Engineering
Classifier: Topic :: Scientific/Engineering :: GIS
Classifier: Topic :: Scientific/Engineering :: Hydrology
Classifier: Typing :: Typed
Requires-Python: >=3.9
Requires-Dist: async-retriever<0.20,>=0.19
Requires-Dist: cytoolz
Requires-Dist: defusedxml
Requires-Dist: joblib
Requires-Dist: multidict
Requires-Dist: orjson<4,>=3.10
Requires-Dist: owslib>=0.27.2
Requires-Dist: pyproj>=3.0.1
Requires-Dist: requests
Requires-Dist: requests-cache>=0.9.6
Requires-Dist: shapely>=2
Requires-Dist: typing-extensions
Requires-Dist: url-normalize>=1.4
Requires-Dist: urllib3
Requires-Dist: yarl
Provides-Extra: test
Requires-Dist: pandas; extra == 'test'
Requires-Dist: pytest-cov; extra == 'test'
Requires-Dist: pytest-sugar; extra == 'test'
